codexpydec/CodexDecoder.py
codexpydec/CodexSchema.py
codexpydec/__init__.py
codexpydec-1.1.2.dist-info/licenses/LICENSE
codexpydec-1.1.2.dist-info/METADATA
codexpydec-1.1.2.dist-info/WHEEL
codexpydec-1.1.2.dist-info/top_level.txt
codexpydec-1.1.2.dist-info/RECORD
