Metadata-Version: 2.4
Name: codexpydec
Version: 1.1.2
Summary: Python implementation of the Codex decoder.
License-Expression: GPL-3.0-only
Project-URL: Homepage, https://github.com/RecursiveInk/codexpydec
Project-URL: Documentation, https://github.com/RecursiveInk/codexpydec
Classifier: Programming Language :: Python :: 3
Classifier: Operating System :: OS Independent
Classifier: Development Status :: 5 - Production/Stable
Classifier: Topic :: File Formats
Classifier: Topic :: System :: Archiving :: Compression
Requires-Python: >=3.10
License-File: LICENSE
Provides-Extra: lzfse
Requires-Dist: pyliblzfse>=0.4.1; extra == "lzfse"
Dynamic: license-file
